<annotation>
	<folder>green</folder>
	<filename>3_650.png</filename>
	<path>C:\Data\sim_2\sim_2\final\green\3_650.png</path>
	<source>
		<database>Unknown</database>
	</source>
	<size>
		<width>800</width>
		<height>600</height>
		<depth>3</depth>
	</size>
	<segmented>0</segmented>
	<object>
		<name>Green</name>
		<pose>Unspecified</pose>
		<truncated>0</truncated>
		<difficult>0</difficult>
		<bndbox>
			<xmin>80</xmin>
			<ymin>143</ymin>
			<xmax>145</xmax>
			<ymax>302</ymax>
		</bndbox>
	</object>
	<object>
		<name>Green</name>
		<pose>Unspecified</pose>
		<truncated>0</truncated>
		<difficult>0</difficult>
		<bndbox>
			<xmin>404</xmin>
			<ymin>154</ymin>
			<xmax>469</xmax>
			<ymax>309</ymax>
		</bndbox>
	</object>
</annotation>
