<annotation verified="yes">
	<folder>yellow</folder>
	<filename>1_20.png</filename>
	<path>/home/william/Downloads/simulator_steps/final/yellow/1_20.png</path>
	<source>
		<database>Unknown</database>
	</source>
	<size>
		<width>800</width>
		<height>600</height>
		<depth>3</depth>
	</size>
	<segmented>0</segmented>
	<object>
		<name>Yellow</name>
		<pose>Unspecified</pose>
		<truncated>0</truncated>
		<difficult>0</difficult>
		<bndbox>
			<xmin>112</xmin>
			<ymin>237</ymin>
			<xmax>168</xmax>
			<ymax>366</ymax>
		</bndbox>
	</object>
	<object>
		<name>Yellow</name>
		<pose>Unspecified</pose>
		<truncated>0</truncated>
		<difficult>0</difficult>
		<bndbox>
			<xmin>374</xmin>
			<ymin>240</ymin>
			<xmax>433</xmax>
			<ymax>370</ymax>
		</bndbox>
	</object>
	<object>
		<name>Yellow</name>
		<pose>Unspecified</pose>
		<truncated>0</truncated>
		<difficult>0</difficult>
		<bndbox>
			<xmin>638</xmin>
			<ymin>245</ymin>
			<xmax>697</xmax>
			<ymax>374</ymax>
		</bndbox>
	</object>
</annotation>
